Workbook

Sheet Supuestos
A1: Supuestos del proyecto - SIGC
A3: Tasa de descuento anual | B3: 0.25
A4: Horizonte de evaluacion (anios) | B4: 5
A5: Crecimiento anual de beneficios | B5: 0.08
A6: Inversion inicial total | B6: =Inversion!B11
A7: Costos operativos anuales | B7: =Costos!B8
A8: Beneficios del anio 1 | B8: =Beneficios!B8
A11: Nota: caso sin inflacion; valores en pesos corrientes constantes.

Sheet Inversion
A1: Inversion inicial (Anio 0)
A2: Concepto | B2: Monto
A3: Implementacion del sistema | B3: 4200000
A4: Configuracion e integraciones | B4: 2600000
A5: Equipamiento y lectores de codigo de barras | B5: 2200000
A6: Migracion de datos | B6: 1000000
A7: Capacitacion inicial | B7: 800000
A8: Contingencia | B8: 1200000
A9: Total inversion inicial | B9: =SUM(B3:B8)

Sheet Costos
A1: Costos operativos anuales
A2: Concepto | B2: Monto anual
A3: Licencias y soporte | B3: 3600000
A4: Hosting / infraestructura | B4: 700000
A5: Mantenimiento y ajustes | B5: 500000
A6: Capacitacion continua | B6: 300000
A7: Total costos operativos anuales | B7: =SUM(B3:B6)

Sheet Beneficios
A1: Beneficios proyectados
A2: Concepto (beneficio anio 1) | B2: Monto
A3: Ahorro de horas administrativas | B3: 4800000
A4: Reduccion de errores y reprocesos | B4: 1500000
A5: Menores perdidas por stock mal gestionado | B5: 2000000
A6: Margen adicional por mejora en ventas | B6: 3000000
A7: Total beneficios anio 1 | B7: =SUM(B3:B6)
A11: Proyeccion de beneficios (crecimiento 8% anual)
A12: Anio | B12: 1 | C12: 2 | D12: 3 | E12: 4 | F12: 5
A13: Beneficios | B13: =B8 | C13: =B13*(1+Supuestos!$B$5) | D13: =C13*(1+Supuestos!$B$5) | E13: =D13*(1+Supuestos!$B$5) | F13: =E13*(1+Supuestos!$B$5)

Sheet Flujo de fondos
A1: Flujo de fondos del proyecto (5 anios)
A3: Concepto | B3: Anio 0 | C3: Anio 1 | D3: Anio 2 | E3: Anio 3 | F3: Anio 4 | G3: Anio 5
A4: Inversion inicial | B4: =-Inversion!B11 | C4: 0 | D4: 0 | E4: 0 | F4: 0 | G4: 0
A5: Beneficios | B5: 0 | C5: ='Beneficios'!B14 | D5: ='Beneficios'!C14 | E5: ='Beneficios'!D14 | F5: ='Beneficios'!E14 | G5: ='Beneficios'!F14
A6: Costos operativos | B6: 0 | C6: =-Costos!$B$8 | D6: =-Costos!$B$8 | E6: =-Costos!$B$8 | F6: =-Costos!$B$8 | G6: =-Costos!$B$8
A7: Flujo neto | B7: =B4+B5+B6 | C7: =C4+C5+C6 | D7: =D4+D5+D6 | E7: =E4+E5+E6 | F7: =F4+F5+F6 | G7: =G4+G5+G6
A8: Flujo descontado (25%) | B8: =B7/(1+Supuestos!$B$3)^0 | C8: =C7/(1+Supuestos!$B$3)^1 | D8: =D7/(1+Supuestos!$B$3)^2 | E8: =E7/(1+Supuestos!$B$3)^3 | F8: =F7/(1+Supuestos!$B$3)^4 | G8: =G7/(1+Supuestos!$B$3)^5
A9: Flujo acumulado | B9: =B7 | C9: =B9+C7 | D9: =C9+D7 | E9: =D9+E7 | F9: =E9+F7 | G9: =F9+G7
A10: Flujo acumulado descontado | B10: =B8 | C10: =B10+C8 | D10: =C10+D8 | E10: =D10+E8 | F10: =E10+F8 | G10: =F10+G8
A13: Indicadores de evaluacion
A14: VAN (Valor Actual Neto, 25%) | B14: =B7+NPV(Supuestos!$B$3,C7:G7)
A15: TIR (Tasa Interna de Retorno) | B15: =IRR(B7:G7)
A16: Payback simple (anios) | B16: 1.82
A17: Payback descontado (anios) | B17: 2.6
A18: Payback calculado a partir de las filas de flujo acumulado.

Sheet Sensibilidad
A1: Analisis de sensibilidad (VAN)
A3: VAN segun tasa de descuento | D3: VAN segun nivel de beneficios (tasa 25%)
A4: Tasa | B4: VAN | D4: Escenario | E4: VAN
A5: 0.15 | B5: ='Flujo de fondos'!B7+NPV(0.15,'Flujo de fondos'!C7:G7) | D5: Beneficios -20% | E5: =-Inversion!B11+SUMPRODUCT((Beneficios!B14:F14*0.8-Costos!B8),1/(1+0.25)^{1,2,3,4,5})
A6: 0.2 | B6: ='Flujo de fondos'!B7+NPV(0.2,'Flujo de fondos'!C7:G7) | D6: Beneficios -10% | E6: =-Inversion!B11+SUMPRODUCT((Beneficios!B14:F14*0.9-Costos!B8),1/(1+0.25)^{1,2,3,4,5})
A7: 0.25 | B7: ='Flujo de fondos'!B7+NPV(0.25,'Flujo de fondos'!C7:G7) | D7: Base (100%) | E7: =-Inversion!B11+SUMPRODUCT((Beneficios!B14:F14*1.0-Costos!B8),1/(1+0.25)^{1,2,3,4,5})
A8: 0.3 | B8: ='Flujo de fondos'!B7+NPV(0.3,'Flujo de fondos'!C7:G7) | D8: Beneficios +10% | E8: =-Inversion!B11+SUMPRODUCT((Beneficios!B14:F14*1.1-Costos!B8),1/(1+0.25)^{1,2,3,4,5})
A9: 0.35 | B9: ='Flujo de fondos'!B7+NPV(0.35,'Flujo de fondos'!C7:G7) | D9: Beneficios +20% | E9: =-Inversion!B11+SUMPRODUCT((Beneficios!B14:F14*1.2-Costos!B8),1/(1+0.25)^{1,2,3,4,5})
A10: 0.4 | B10: ='Flujo de fondos'!B7+NPV(0.4,'Flujo de fondos'!C7:G7)
